{
    "Ar36": {
        "error": 0.0003017454467962303,
        "error_type": "",
        "fit": "previous",
        "references": [
            {
                "exclude": false,
                "record_id": "ba-01-A-32138"
            }
        ],
        "value": 0.016765788529570596
    },
    "Ar37": {
        "error": 0.009060080019035105,
        "error_type": "",
        "fit": "previous",
        "references": [
            {
                "exclude": false,
                "record_id": "ba-01-A-32138"
            }
        ],
        "value": 0.022675114570804504
    },
    "Ar38": {
        "error": 0.01138391118836308,
        "error_type": "",
        "fit": "previous",
        "references": [
            {
                "exclude": false,
                "record_id": "ba-01-A-32138"
            }
        ],
        "value": 0.027695359301121512
    },
    "Ar39": {
        "error": 0.009308538430091698,
        "error_type": "",
        "fit": "previous",
        "references": [
            {
                "exclude": false,
                "record_id": "ba-01-A-32138"
            }
        ],
        "value": 0.059317488289477
    },
    "Ar40": {
        "error": 0.02192549199771703,
        "error_type": "",
        "fit": "previous",
        "references": [
            {
                "exclude": false,
                "record_id": "ba-01-A-32138"
            }
        ],
        "value": 4.443745567719965
    }
}